MLStacker/__init__.py
MLStacker/stack_model.py
MLStacker-0.0.1.dist-info/DESCRIPTION.rst
MLStacker-0.0.1.dist-info/METADATA
MLStacker-0.0.1.dist-info/RECORD
MLStacker-0.0.1.dist-info/WHEEL
MLStacker-0.0.1.dist-info/metadata.json
MLStacker-0.0.1.dist-info/top_level.txt
