Metadata-Version: 2.0
Name: MLStacker
Version: 0.0.1
Summary: A package which supports the implementation of stacking of machine learning models
Home-page: https://github.com/nicholaslaw/ModelStacker
Author: Nicholas Law
Author-email: nicholas_law_91@hotmail.com
License: UNKNOWN
Platform: UNKNOWN
Classifier: Programming Language :: Python :: 3
Classifier: License :: OSI Approved :: MIT License
Classifier: Operating System :: OS Independent
Requires-Dist: numpy (==1.14.0)
Requires-Dist: pandas (==0.22.0)
